doctomarkdown/__init__.py
doctomarkdown/base.py
doctomarkdown/converters/__init__.py
doctomarkdown/converters/csv_to_markdown.py
doctomarkdown/converters/docx_to_markdown.py
doctomarkdown/converters/image_to_markdown.py
doctomarkdown/converters/pdf_to_markdown.py
doctomarkdown/converters/pptx_to_markdown.py
doctomarkdown/converters/url_to_markdown.py
doctomarkdown/llmwrappers/ExceptionWrapper.py
doctomarkdown/llmwrappers/GeminiWrapper.py
doctomarkdown/llmwrappers/__init__.py
doctomarkdown/utils/__init__.py
doctomarkdown/utils/content_to_markdown.py
doctomarkdown/utils/markdown_helpers.py
doctomarkdown/utils/pptx_to_pdf.py
doctomarkdown/utils/prompts.py
doctomarkdown/utils/site_extractor.py
doctomarkdown-0.2.0.dist-info/licenses/LICENSE
tests/__init__.py
tests/test_factory.py
tests/test_pdf.py
doctomarkdown-0.2.0.dist-info/METADATA
doctomarkdown-0.2.0.dist-info/WHEEL
doctomarkdown-0.2.0.dist-info/top_level.txt
doctomarkdown-0.2.0.dist-info/RECORD
