Metadata-Version: 2.4
Name: doctomarkdown
Version: 0.2.0
Summary: Convert PDF, DOCX, PPTX, Images, URLs like Medium, Wikipedia and CSV documents to text or Markdown. Extracts text, images, and tables. Supports LLM-based extraction.
Home-page: https://github.com/DocParseAI/doctomarkdown
Author: docparseai
Author-email: docparseai <sayantanghosh.work@gmail.com>
License: MIT License
Project-URL: Homepage, https://github.com/DocParseAI/doctomarkdown
Project-URL: Documentation, https://github.com/DocParseAI/doctomarkdown#readme
Project-URL: BugTracker, https://github.com/DocParseAI/doctomarkdown/issues
Project-URL: PyPI, https://pypi.org/project/doctomarkdown/
Requires-Python: >=3.10
License-File: LICENSE
Requires-Dist: PyMuPDF
Requires-Dist: Pillow
Requires-Dist: typing-extensions
Requires-Dist: python-docx
Requires-Dist: python-pptx
Requires-Dist: pandas
Requires-Dist: tabulate
Requires-Dist: html2text
Requires-Dist: beautifulsoup4
Requires-Dist: google-generativeai
Requires-Dist: pytesseract
Requires-Dist: comtypes
Requires-Dist: docx2pdf
Dynamic: author
Dynamic: home-page
Dynamic: license-file
Dynamic: requires-python
